pytagimg/__init__.py
pytagimg/configs.py
pytagimg/main.py
pytagimg/static.py
pytagimg-0.0.4.dist-info/LICENSE
pytagimg-0.0.4.dist-info/METADATA
pytagimg-0.0.4.dist-info/WHEEL
pytagimg-0.0.4.dist-info/entry_points.txt
pytagimg-0.0.4.dist-info/top_level.txt
pytagimg-0.0.4.dist-info/RECORD
